ds_resource_plugin_py_lib/__init__.py
ds_resource_plugin_py_lib/py.typed
ds_resource_plugin_py_lib/common/__init__.py
ds_resource_plugin_py_lib/common/resource/__init__.py
ds_resource_plugin_py_lib/common/resource/client.py
ds_resource_plugin_py_lib/common/resource/errors.py
ds_resource_plugin_py_lib/common/resource/dataset/__init__.py
ds_resource_plugin_py_lib/common/resource/dataset/base.py
ds_resource_plugin_py_lib/common/resource/dataset/errors.py
ds_resource_plugin_py_lib/common/resource/dataset/storage_format.py
ds_resource_plugin_py_lib/common/resource/linked_service/__init__.py
ds_resource_plugin_py_lib/common/resource/linked_service/base.py
ds_resource_plugin_py_lib/common/resource/linked_service/errors.py
ds_resource_plugin_py_lib/common/serde/__init__.py
ds_resource_plugin_py_lib/common/serde/deserialize/__init__.py
ds_resource_plugin_py_lib/common/serde/deserialize/awswrangler.py
ds_resource_plugin_py_lib/common/serde/deserialize/base.py
ds_resource_plugin_py_lib/common/serde/deserialize/pandas.py
ds_resource_plugin_py_lib/common/serde/serialize/__init__.py
ds_resource_plugin_py_lib/common/serde/serialize/awswrangler.py
ds_resource_plugin_py_lib/common/serde/serialize/base.py
ds_resource_plugin_py_lib/common/serde/serialize/pandas.py
ds_resource_plugin_py_lib/libs/__init__.py
ds_resource_plugin_py_lib/libs/utils/import_string.py
ds_resource_plugin_py_lib-0.1.0a2.dist-info/licenses/LICENSE-APACHE
ds_resource_plugin_py_lib-0.1.0a2.dist-info/METADATA
ds_resource_plugin_py_lib-0.1.0a2.dist-info/WHEEL
ds_resource_plugin_py_lib-0.1.0a2.dist-info/top_level.txt
ds_resource_plugin_py_lib-0.1.0a2.dist-info/RECORD
