Metadata-Version: 2.4
Name: ds-resource-plugin-py-lib
Version: 0.1.0a2
Summary: A Python package from the ds-common library collection
Author-email: Kristoffer Varslott <hello@grasplabs.com>
Maintainer-email: Kristoffer Varslott <hello@grasplabs.com>
License-Expression: Apache-2.0
Project-URL: Documentation, https://grasp-labs.github.io/ds-resource-plugin-py-lib/
Project-URL: Repository, https://github.com/grasp-labs/ds-resource-plugin-py-lib/
Project-URL: Issues, https://github.com/grasp-labs/ds-resource-plugin-py-lib/issues/
Project-URL: Changelog, https://github.com/grasp-labs/ds-resource-plugin-py-lib/releases
Keywords: ds,common,python
Classifier: Development Status :: 3 - Alpha
Classifier: Programming Language :: Python :: 3
Classifier: Programming Language :: Python :: 3.11
Classifier: Programming Language :: Python :: 3.12
Classifier: Programming Language :: Python :: 3.13
Classifier: Operating System :: OS Independent
Classifier: Intended Audience :: Developers
Classifier: Topic :: Software Development :: Libraries :: Python Modules
Requires-Python: >=3.11
License-File: LICENSE-APACHE
Requires-Dist: pandas<3.0.0,>=2.1.0
Requires-Dist: awswrangler<4.0.0,>=3.11.0
Requires-Dist: pyyaml<7.0.0,>=6.0.2
Requires-Dist: typing-extensions<5.0.0,>=4.0.0
Requires-Dist: ds-common-logger-py-lib<1.0.0,>=0.1.0a1
Requires-Dist: ds-common-serde-py-lib<1.0.0,>=0.1.0a2
Provides-Extra: dev
Requires-Dist: ruff>=0.1.8; extra == "dev"
Requires-Dist: mypy>=1.7.0; extra == "dev"
Requires-Dist: pandas-stubs>=2.1.0; extra == "dev"
Requires-Dist: types-PyYAML>=6.0.0; extra == "dev"
Requires-Dist: pytest>=7.4.0; extra == "dev"
Requires-Dist: pytest-cov>=4.1.0; extra == "dev"
Requires-Dist: pytest-xdist>=3.3.0; extra == "dev"
Requires-Dist: pre-commit>=3.6.0; extra == "dev"
Requires-Dist: build>=1.0.0; extra == "dev"
Requires-Dist: twine>=4.0.0; extra == "dev"
Requires-Dist: sphinx>=7.1.0; extra == "dev"
Requires-Dist: sphinx-autoapi>=3.0.0; extra == "dev"
Requires-Dist: sphinx-material>=0.0.35; extra == "dev"
Provides-Extra: test
Requires-Dist: pytest>=7.4.0; extra == "test"
Requires-Dist: pytest-cov>=4.1.0; extra == "test"
Requires-Dist: pytest-xdist>=3.3.0; extra == "test"
Provides-Extra: docs
Requires-Dist: sphinx>=7.1.0; extra == "docs"
Requires-Dist: sphinx-autoapi>=3.0.0; extra == "docs"
Requires-Dist: sphinx-material>=0.0.35; extra == "docs"
Dynamic: license-file
